{
 "cells": [
  {
   "cell_type": "markdown",
   "metadata": {},
   "source": [
    "# 第二章 Java内存区域与内存溢出异常"
   ]
  },
  {
   "cell_type": "markdown",
   "metadata": {},
   "source": [
    "## Java内存分类\n",
    "\n",
    "Java的内存可以分为为两大类：\n",
    "\n",
    "1. 线程隔离区域：这个区域中不同线程对应的内存区域是分开的，彼此是相互隔离的，主要是三个区域：\n",
    "   1. 程序计数器：主要用于指示程序运行的位置，是一个累加器一样的东西。应用场景是在多线程并发，线程切换时能够让线程在程序计数器的作用下找到程序执行的位置。因此不同线程的程序计数器是彼此隔离的。\n",
    "   2. Java虚拟机栈：这个区域也是线程隔离的，也叫做Java栈，用于维护各个线程中的方法内存模型，每个方法在执行时会向虚拟机栈中压入一个栈帧，该栈帧中用于存储**局部变量表**，**操作数栈**，**动态链接**等信息。Java中常说的堆栈中的栈指的就是Java虚拟机栈。\n",
    "   3. 本地方发栈：该栈的作用和Java虚拟机栈类似，但是作用的方法对象不是Java方法，而是本地方法，也就是第三方库提供的。\n",
    "2. 非线程隔离的区域：这个区域中不同线程的内存是相互可以访问的，主要是两个区域：\n",
    "   1. Java堆（Heap）：这个内存区域中主要存放各种类型的Java对象，也是Java虚拟机管理的最大一部分内存。Java堆可以是一块连续的内存，也可以是物理上不连续但是逻辑上连续的内存。在Java堆中不同的线程可以共享堆内存，但这可能会引发竞争条件（即A线程的对象释放了某个堆内存，但是在其还没有释放完成时B对象就引用了该内存），也可以将堆内存进行划分，给各线程分别使用，这种技术叫做TLAB.\n",
    "   2. 方法区：该区域用于存放Java类中的类信息，常量，静态变量等等数据。在方法区中还有一块特殊的区域叫做运行时常量池，与一般的常量和变量必须在编译时就确定不同，运行时常量池可以在程序运行期间加入常量，例如使用`String.intern();`就能实现运行时将常量加入到方法区也就是运行时常量池中。\n",
    "\n",
    "## 一个对象的创建流程\n",
    "\n",
    "一个对象的创建流程大致可以做以下表述：\n",
    "\n",
    "1. Java虚拟机首先检查该类是否被装载（load），如果没有则装载该类。一个类一旦被装载就将得知其所需内存大小。\n",
    "\n",
    "2. 类被装载过后就要进行内存申请，内存申请有两种方式：\n",
    "   1. 指针碰撞：这种方式中堆内存是绝对规整的，也就是说使用过的内存在逻辑上被放在一边，没有使用过的逻辑上被放在另一边，两个区域使用一个内存指针隔开，当需要进行新的内存申请时只需要把内存指针偏移指定的距离即可。\n",
    "   2. 空闲列表：这种方式堆内存并不是规整的，Java会维护一个空闲内存表，需要申请内存时只是在空闲内存表中找到一块足够大的空间分配给对象。\n",
    "   \n",
    "   具体采取哪种内存分配策略取决于Java的垃圾回收器是否带有内存压缩机制。\n",
    "   \n",
    "   同时，在多线程并发申请内存时还可能出现内存申请竞争条件，有两个方法来避免这种情况：\n",
    "   1. 对线程申请内存操作进行同步处理。\n",
    "   2. 将不同的线程申请的内存区域隔离开，也就是TLAB技术。不同线程申请的内存区域是不重叠的，也就避免了内存申请的竞争条件。\n",
    "3. Java虚拟机将对申请好内存的对象一些列初始化操作，具体包含两个类型的操作：\n",
    "   1. 进行零值化操作，也就是将所有的布尔型变量初始化为`false`。\n",
    "   2. 对类的对象头进行设置，对象头中包含了类的许多重要信息，包括元数据信息，哈希值等等。\n",
    "4. 最后，再由Java虚拟机运行对象的构造方法，对对象进行必要的初始化操作。"
   ]
  },
  {
   "cell_type": "markdown",
   "metadata": {},
   "source": [
    "## 对象的内存布局\n",
    "\n",
    "一个对象的内存主要分为三个部分：\n",
    "\n",
    "1. 对象头：对象头中存储着对象的重要信息，对象头主要由以下两个部分的信息组成：\n",
    "   1. 第一部分用于存储运行时数据，包括哈希值，锁状态标志，偏向线程ID等等。\n",
    "   2. 第二部分用于存储其类型指针，这个指针指向其类的元数据，用于说明该对象是哪个类的实例化结果。\n",
    "2. 实例数据：这个区域主要用于存放实例对象的各种变量。\n",
    "3. 对齐填充：这个区域不是必须存在的，它主要起到内存占位的作用。这是由于某些Java虚拟机要求对象的内存必须是8字节的整数倍，因此就会有这样的占位内存来满足Java虚拟机的要求。\n",
    "\n",
    "一个对象如何索引到其实例变量和类变量呢？主要是通过Java虚拟机栈中本地变量表中的一个`ref`指针（其实就是`this`指针），使用该指针来索引变量，主要有两种方法：\n",
    "\n",
    "1. 采用句柄的方法：`ref`指针指向Java堆的一个特定区域，该区域中记录着每个Java对象变量和类变量（主要是方法区中常量和静态变量）的起始位置，以此来达到索引的目的：\n",
    "2. 采用直接指针：`ref`指针直接指向Java堆中对象实例变量的内存起始位置，该内存中不仅仅有变量值还有一个指针指向方法区中类变量（只要是常量和静态变量）的起始位置。"
   ]
  },
  {
   "cell_type": "markdown",
   "metadata": {},
   "source": [
    "# 第三章 垃圾收集器与内存分配策略"
   ]
  },
  {
   "cell_type": "markdown",
   "metadata": {},
   "source": [
    "本章主要讲了Java虚拟机中垃圾回收的一些机制，包括垃圾回收算法，回收算法的实现，回收的大致步骤以及内存分配时候的一些规定。对于之前不懂Java虚拟机内部实现的人来说还是大有帮助的，颠覆了一些之前想当然的观念，比如说Java的自动垃圾回收机制是基于引用计数的方式实现的。"
   ]
  },
  {
   "cell_type": "markdown",
   "metadata": {},
   "source": [
    "## Java中的引用类型和可达性分析\n",
    "\n",
    "Java中的自动垃圾回收机制不是使用引用计数实现的，而是使用“可达性”分析的方法。这种方法简而言之就是利用一系列称为`GC Roots`的对象作为起点，从这些起点开始向下搜索，所走过的路径称为引用链，当一个对象没有和任何一个`GC Root`对象通过引用链相连时就说明这个这个对象是不可用的，证明是可以被回收的。Java中能被称之为`GCRoots`对象的有以下四类：\n",
    "\n",
    "* 虚拟机栈（栈帧中的本地变量表）中的引用对象。\n",
    "\n",
    "* 方法区中类静态属性引用对象。\n",
    "\n",
    "* 方法区中常量引用的对象。\n",
    "\n",
    "* 本地方法栈中`JNI`（即一般说的`Native`方法）引用的对象。\n",
    "\n",
    "Java对象的引用分为四种类型：\n",
    "\n",
    "* 强引用：这种引用的程度最强，在垃圾回收的过程中，有强引用的对象不会被回收。\n",
    "\n",
    "* 软引用：比强引用要弱一些，对应那些有用但不是必需的对象，通常在第一次垃圾回收时不会被回收，但是在第二次垃圾回收的过程中会被回收。\n",
    "\n",
    "* 弱引用：比软引用更加弱势，用于指代那些完全没有用的对象，通常在第一次垃圾回收中就会被回收。\n",
    "\n",
    "* 虚引用：这种引用没有任何实际意义，仅仅是在垃圾回收的过程中打印出一条记录。"
   ]
  },
  {
   "cell_type": "markdown",
   "metadata": {},
   "source": [
    "## Java中垃圾回收的一般过程\n",
    "\n",
    "Java中触发垃圾回收的一般过程都是先进行可达性分析，但是这通常要耗费很多时间，而且在进行分析的过程中通常要将所有的线程执行都停下来，因此这会带来很大的性能损失，通常的步骤是：\n",
    "\n",
    "1. 虚拟机再运行时在每个安全点进行一次操作，所谓安全点就是程序即将进行长时间运行的时间点，即进入方法调用之前，进入循环之前等等。在安全点线程会将上一个安全点之间的所有引用对象都加入到一个`oopmap`的对象中，这样虚拟机在进行可达性分析的过程中就能够减少扫描范围。安全点的设置有时候过于苛刻，因此通行的做法是在安全区内进行上述操作，安全区是指某一个代码片段，在这个代码片段中引用关系不会发生变化。\n",
    "\n",
    "2. 触发垃圾回收机制一定在安全点或者安全区，垃圾回收的过程中要将所有的执行线程都停下来，Java虚拟机将会检查所有`GC Root`对象的`oopmap`结构，进行可达性分析，找出不可达的对象来进行垃圾回收。在停止执行线程的方法上有两种中断方式：\n",
    "   1. 抢占式中断：这种中断方式是强制停止所有的线程，然后再恢复那些没有运行到安全点的线程，让他们运行到安全点再停止。\n",
    "   2. 主动式中断：这种中断方式不对线程进行具体操作，仅仅是设置一个标志位让各个线程进行轮询，该标志位是一个自陷信号，线程检测到这个信号就会自动挂起\n",
    "   \n",
    "3. 当所有线程停止运行Java虚拟机在执行最终的垃圾收集之前还将最后做一次检查，即检查将要被回收对象的`finalize`方法，如果对象实现了这个方法而且没有被虚拟机执行过，那么就会被虚拟机执行这个方法，在这个方法中程序员只要让这个对象再被其他对象引用就能够避免该对象被回收。但是这个方法并不被虚拟机保证执行，而且执行的优先级非常低，因此不推荐这种方式来避免对象被回收。\n",
    "\n",
    "4. 在对对象进行垃圾回收时有三类算法：\n",
    "   1. 标记清理算法：这种算法只是简单地将被回收的对象从内存中清除，这种算法将会带来大量的内存碎片，非常不友好。\n",
    "   2. 复制算法：这种清理算法应用的比较多，一个比较经典的实现是IBM开发的垃圾回收算法，这种算法假定所有的新生代对象大多都是“朝生夕死”，因此将堆中的新生代区域分成了三个部分，一个$Eden$区域和两个$survivor$区域，其中$Eden$区域和$survivor$区域的大小比为8:1，日常只有一个$Eden$区和一个$survivor$区参与内存的分配和回收，另一个$survivor$区空闲。当发生内存回收的时候虚拟机首先将$Eden$和$survivor$区中的对象清除掉，然后将剩余的对象复制到闲置的$survivor$区域中，最后将$Eden$和$survivor$区域的内存清空。如果闲置的$survivor$区域空间不足，将会触发从老年代内存区域中“借”内存的操作。\n",
    "   3. 标记整理算法：这种算法是针对老年代对象的，老年代对象一般是指那种长期存在，被清理频率很低的对象，他们和新生代对象的存放位置也不一样，虽然都是在堆中，但是在不同的区域。触发老年代对象回收的时候，虚拟机将会把所有的存活对象进行压紧操作，达到清除内存碎片的目的。由于老年代对象的回收不频繁，因此这样的操作带来的性能下降也可以被容忍。"
   ]
  },
  {
   "cell_type": "markdown",
   "metadata": {},
   "source": [
    "## Java中的内存分配过程\n",
    "\n",
    "Java中的内存分配也遵循着比较复杂的过程。对象一般在Java堆中进行内存分配，由于虚拟机采用的分代回收算法，虚拟机将堆内存分为新生代和老年代。所谓新生代就是存放那些很快被创建又很快被销毁的对象，这些对象的生命周期一般都很短。老年代对象指的是那些将会较长时间存在的对象。当然，新生代对象和老年代对象并不是人为指定的，而是在运行过程中由虚拟机指定的。\n",
    "\n",
    "在Java虚拟机中可以用参数来规定虚拟机中新生代区域的大小和老年代区域的大小，新生代区域中一般遵从复制垃圾回收算法，即分配一个$Eden$空间两个$survivor$空间，且$Eden$空间和$survivor$空间的大小之比为8:1。\n",
    "\n",
    "当一个对象要申请内存时遵循以下步骤：\n",
    "\n",
    "1. 新生成的对象首先在$Eden$空间中分配内存，如果$Eden$空间不足则会触发垃圾回收，将$Eden$空间中的部分内存释放，同时将活着的对象复制到$survivor$空间中。\n",
    "\n",
    "2. 如果新生的对象所占内存过于庞大，无法在新生代中安放，或者其大小超过了用户设定的最大值，那么该对象直接会被放入老年代内存区域中。\n",
    "\n",
    "3. 在新生代区域中存在的对象如果在多次垃圾回收中都未被清理就会被虚拟机标记为长期存在的对象进而被放入老年代区域存储，事实上，每一次垃圾回收的过程都会给未被回收的对象的年龄计数器加一，通常年龄计数器的值大于15就会被认为是老年代对象。\n",
    "\n",
    "4. 如果在新生代中的对象相同年龄的对象达到了$survivor$空间的一半，那么这些对象就会被放入老年代中。\n",
    "\n",
    "5. 在复制算法中，算法设计者假定新生代对象在每一次垃圾回收中仅仅有2%被保留，因此$survivor$的空间在整个新生代中只占10%。难免会出现剩余的新生代对象大小大于$survivor$能承载的极限。这时候就要将多余的对象从新生代区域转入老年代区域，如果此时老年代区域的连续内存大于要转入的部分，那么可以直接操作。否则就有可能出现老年代区域装不下新生代对象的情况，这时候虚拟机会尝试着向老年代区域复制，如果失败则启动老年代区域的垃圾回收。"
   ]
  },
  {
   "cell_type": "markdown",
   "metadata": {},
   "source": [
    "# 第六章 类文件结构"
   ]
  },
  {
   "cell_type": "markdown",
   "metadata": {},
   "source": [
    "## 背景知识\n",
    "\n",
    ">`Class`文件是一组以8字节为基础单位的二进制流，各个数据项目严格按照顺序紧凑排列在`Class`文件中。\n",
    "\n",
    "> 无符号数属于基本数据类型，以`u1`,`u2`,`u4`,`u8`分别代表一个字节，两个字节，四个字节和八个字节的无符号数，无符号数可以用来描述数字，索引引用，数量值或者按照UTF8编码构成的字符串值。"
   ]
  },
  {
   "cell_type": "markdown",
   "metadata": {},
   "source": [
    "本章以以下Java代码为例：\n",
    "\n",
    "```Java\n",
    "public class App {\n",
    "    private int m;\n",
    "    private int n = 123;\n",
    "    public int inc(){\n",
    "        return m + 1;\n",
    "    }\n",
    "}\n",
    "```"
   ]
  },
  {
   "cell_type": "markdown",
   "metadata": {},
   "source": [
    "然后使用`javac`对其进行编译，得到如下字节码：\n",
    "\n",
    "```shell\n",
    "offset |  0   1   2   3   4   5   6   7   8   9   A   B   C   D   E   F\n",
    "-----------------------------------------------------------------------\n",
    "0x0000 | CA  FE  BA  BE  00  00  00  37  00  16  0A  00  05  00  11  09  \n",
    "0x0010 | 00  04  00  12  09  00  04  00  13  07  00  14  07  00  15  01  \n",
    "0x0020 | 00  01  6D  01  00  01  49  01  00  01  6E  01  00  06  3C  69  \n",
    "0x0030 | 6E  69  74  3E  01  00  03  28  29  56  01  00  04  43  6F  64  \n",
    "0x0040 | 65  01  00  0F  4C  69  6E  65  4E  75  6D  62  65  72  54  61  \n",
    "0x0050 | 62  6C  65  01  00  03  69  6E  63  01  00  03  28  29  49  01  \n",
    "0x0060 | 00  0A  53  6F  75  72  63  65  46  69  6C  65  01  00  08  41  \n",
    "0x0070 | 70  70  2E  6A  61  76  61  0C  00  09  00  0A  0C  00  08  00  \n",
    "0x0080 | 07  0C  00  06  00  07  01  00  03  41  70  70  01  00  10  6A  \n",
    "0x0090 | 61  76  61  2F  6C  61  6E  67  2F  4F  62  6A  65  63  74  00  \n",
    "0x00A0 | 21  00  04  00  05  00  00  00  02  00  02  00  06  00  07  00  \n",
    "0x00B0 | 00  00  02  00  08  00  07  00  00  00  02  00  01  00  09  00  \n",
    "0x00C0 | 0A  00  01  00  0B  00  00  00  27  00  02  00  01  00  00  00  \n",
    "0x00D0 | 0B  2A  B7  00  01  2A  10  7B  B5  00  02  B1  00  00  00  01  \n",
    "0x00E0 | 00  0C  00  00  00  0A  00  02  00  00  00  01  00  04  00  04  \n",
    "0x00F0 | 00  01  00  0D  00  0E  00  01  00  0B  00  00  00  1F  00  02  \n",
    "0x0100 | 00  01  00  00  00  07  2A  B4  00  03  04  60  AC  00  00  00  \n",
    "0x0110 | 01  00  0C  00  00  00  06  00  01  00  00  00  06  00  01  00  \n",
    "0x0020 | 0F  00  00  00  02  00  10\n",
    "```"
   ]
  },
  {
   "cell_type": "markdown",
   "metadata": {},
   "source": [
    "使用Java自带的字节码分析工具`javap`进行分析得到如下结果：\n",
    "\n",
    "```shell\n",
    "F:\\>javap -verbose App\n",
    "Classfile /F:/App.class\n",
    "  Last modified 2019年3月21日; size 295 bytes\n",
    "  MD5 checksum 93f039dc66d5bde9c66e5eaeae9bbe99\n",
    "  Compiled from \"App.java\"\n",
    "public class App\n",
    "  minor version: 0\n",
    "  major version: 55\n",
    "  flags: (0x0021) ACC_PUBLIC, ACC_SUPER\n",
    "  this_class: #4                          // App\n",
    "  super_class: #5                         // java/lang/Object\n",
    "  interfaces: 0, fields: 2, methods: 2, attributes: 1\n",
    "Constant pool:\n",
    "   #1 = Methodref          #5.#17         // java/lang/Object.\"<init>\":()V\n",
    "   #2 = Fieldref           #4.#18         // App.n:I\n",
    "   #3 = Fieldref           #4.#19         // App.m:I\n",
    "   #4 = Class              #20            // App\n",
    "   #5 = Class              #21            // java/lang/Object\n",
    "   #6 = Utf8               m\n",
    "   #7 = Utf8               I\n",
    "   #8 = Utf8               n\n",
    "   #9 = Utf8               <init>\n",
    "  #10 = Utf8               ()V\n",
    "  #11 = Utf8               Code\n",
    "  #12 = Utf8               LineNumberTable\n",
    "  #13 = Utf8               inc\n",
    "  #14 = Utf8               ()I\n",
    "  #15 = Utf8               SourceFile\n",
    "  #16 = Utf8               App.java\n",
    "  #17 = NameAndType        #9:#10         // \"<init>\":()V\n",
    "  #18 = NameAndType        #8:#7          // n:I\n",
    "  #19 = NameAndType        #6:#7          // m:I\n",
    "  #20 = Utf8               App\n",
    "  #21 = Utf8               java/lang/Object\n",
    "{\n",
    "  public App();\n",
    "    descriptor: ()V\n",
    "    flags: (0x0001) ACC_PUBLIC\n",
    "    Code:\n",
    "      stack=2, locals=1, args_size=1\n",
    "         0: aload_0\n",
    "         1: invokespecial #1                  // Method java/lang/Object.\"<init>\":()V\n",
    "         4: aload_0\n",
    "         5: bipush        123\n",
    "         7: putfield      #2                  // Field n:I\n",
    "        10: return\n",
    "      LineNumberTable:\n",
    "        line 1: 0\n",
    "        line 4: 4\n",
    "\n",
    "  public int inc();\n",
    "    descriptor: ()I\n",
    "    flags: (0x0001) ACC_PUBLIC\n",
    "    Code:\n",
    "      stack=2, locals=1, args_size=1\n",
    "         0: aload_0\n",
    "         1: getfield      #3                  // Field m:I\n",
    "         4: iconst_1\n",
    "         5: iadd\n",
    "         6: ireturn\n",
    "      LineNumberTable:\n",
    "        line 6: 0\n",
    "}\n",
    "SourceFile: \"App.java\"\n",
    "```"
   ]
  },
  {
   "cell_type": "markdown",
   "metadata": {},
   "source": [
    "## 总体结构\n",
    "\n",
    "* 魔数：用于标识字节码文件的特定信息，一共有4个字节，使用16进制表示为`0xCAFEBABE`。\n",
    "* 版号：用于标识该字节码文件是由什么版本的虚拟机编译而成的。\n",
    "* 常量池：存放该字节码文件中所要用到的全部常量，在常量池中常量的索引从1开始。\n",
    "  1. 常量个数：使用2个字节标识常量池中常量的个数，真实的个数是该字段值减一。\n",
    "  2. 常量：JDK1.7中一共定义了11中常量，用于字节码中各个部分使用。\n",
    "* 访问标志：用于标识该类的访问信息，包括该类是否为`private`，是否有`final`关键字修饰。\n",
    "* 类索引：用于标识该类的名称，该类的父类，以及该类所实现的接口。\n",
    "  1. 本类索引：索引到常量池中的一个常量，标识该类的字符串名称。\n",
    "  2. 父类索引：索引到常量池的一个`CONSTANT_Class_info`常量，标识该类的父类字符串名称。\n",
    "  3. 接口索引数目：由于一个类可以实现多个接口，因此该字段用于标识接口索引集中接口的数目。\n",
    "  4. 接口索引（可选）：用于索引到常量池的一个常量，标识接口名称。\n",
    "* 字段表集合：用于标识该类中所有的字段信息。\n",
    "  1. 字段表集合数目：标识字段表集合的数目。\n",
    "  2. 字段表：用于描述一个字段的具体信息，包括访问控制，类型，名称等等。\n",
    "* 方法表集合：用于标识该类中所有的方法信息。\n",
    "  1. 方法表集合大小：用于标识方法表集合中方法表的数目。\n",
    "  2. 方法表：描述一个方法的简单名，描述符，访问控制信息以及代码信息等。\n",
    "* 类属性：描述类的一些特性，比如原文件名称等。"
   ]
  },
  {
   "cell_type": "markdown",
   "metadata": {},
   "source": [
    "## 字节码文件详细结构"
   ]
  },
  {
   "cell_type": "markdown",
   "metadata": {},
   "source": [
    "Java源代码编译而成的字节码按照非常紧凑的结构组成，被Java虚拟机按照字节为单位进行解释。Java字节码的组成部分按照出现先后顺序如下所示：\n",
    "\n",
    "### 魔数\n",
    "\n",
    "这是Java字节码中一个标识符号，意在告诉Java虚拟机这是一个字节码文件。它的取值是固定的：字节码文件的开头四个字节，以十六进制解析成`0xCAFEBABE`字样，不知道是不是呼应了Java语言的logo。\n",
    "\n",
    "```shell\n",
    "offset |  0   1   2   3   4   5   6   7   8   9   A   B   C   D   E   F\n",
    "-----------------------------------------------------------------------\n",
    "0x0000 | CA  FE  BA  BE  ...\n",
    "```"
   ]
  },
  {
   "cell_type": "markdown",
   "metadata": {},
   "source": [
    "### 版号\n",
    "\n",
    "版号字段紧接着魔数字段，用四个字节来表示，意在表明该字节码文件使用什么版本的虚拟机编译而来。通常JDK1.1虚拟机的编号为45，以后每一个大版本的JDK都在版号后加一，例如JDK1.11的版号就为55。\n",
    "\n",
    "```shell\n",
    "offset |  0   1   2   3   4   5   6   7   8   9   A   B   C   D   E   F\n",
    "-----------------------------------------------------------------------\n",
    "0x0000 |            ...  00  00  00  37  ...\n",
    "```"
   ]
  },
  {
   "cell_type": "markdown",
   "metadata": {},
   "source": [
    "上面的字节码的版号为`0x0037`，转化为十进制就是55，表明该字节码使用JDK1.11编译而来。"
   ]
  },
  {
   "cell_type": "markdown",
   "metadata": {},
   "source": [
    "### 常量池\n",
    "\n",
    "字节码的接下来部分用于表示常量。常量在字节码文件中起到表示常量，标识字段意义的作用，例如存储方法名字符串，说明字节码的某个部分是什么意义等作用。在具体的常量表开始之前，字节码首先使用两个字节表示常量池的长度，需要注意的是常量池中的常量以`1`为开始索引，而不是通常的`0`，因此真是的常量个数是字节码中常量池个数的减一。\n",
    "\n",
    "#### 常量池个数\n",
    "\n",
    "```shell\n",
    "offset |  0   1   2   3   4   5   6   7   8   9   A   B   C   D   E   F\n",
    "-----------------------------------------------------------------------\n",
    "0x0000 |                                ...  00  16   ...\n",
    "```\n",
    "可以看到：该字节码的常量池个数是`0x16`，则真正的常量个数为`0x16(22)-1=21`个。"
   ]
  },
  {
   "cell_type": "markdown",
   "metadata": {},
   "source": [
    "#### 常量\n",
    "\n",
    "字节码中的常量也是按照字节紧凑排列的，JDK1.7中一共规定了11中结构不同的常量。以该字节码文件为例："
   ]
  },
  {
   "cell_type": "markdown",
   "metadata": {},
   "source": [
    "```shell\n",
    "offset |  0   1   2   3   4   5   6   7   8   9   A   B   C   D   E   F\n",
    "-----------------------------------------------------------------------\n",
    "0x0000 |                                    ...  0A  00  05  00  11  ...\n",
    "```\n",
    "可以看到，该常量的`tag`值为`0x0A`查表得，该常量类型为`CONSTANT_Methodref_info`，其表结构为：\n",
    "\n",
    "|项目|类型|描述|\n",
    "|:-:|:-:|:-:|\n",
    "|tag|u1|取值为10|\n",
    "|index|u2|指向声明方法的类描述符`CONSTANT_Class_info`的索引项|\n",
    "|index|u2|指向名称及类型描述符`CONSTANT_NameAndType`的索引项|"
   ]
  },
  {
   "cell_type": "markdown",
   "metadata": {},
   "source": [
    "由字节码中的信息可以看到，该`CONSTANT_Methodref_info`的第一个索引值为`0x0005`，第二个索引值为`17(0x0011)`，分别代表了常量池中的第5个常量和第17个常量。查看`javap`中输出的信息：\n",
    "\n",
    "```shell\n",
    "...\n",
    "   #1 = Methodref          #5.#17         // java/lang/Object.\"<init>\":()V\n",
    "   #2 = Fieldref           #4.#18         // App.n:I\n",
    "   #3 = Fieldref           #4.#19         // App.m:I\n",
    "   #4 = Class              #20            // App\n",
    "   #5 = Class              #21            // java/lang/Object\n",
    "   #6 = Utf8               m\n",
    "   #7 = Utf8               I\n",
    "   #8 = Utf8               n\n",
    "   #9 = Utf8               <init>\n",
    "  #10 = Utf8               ()V\n",
    "  #11 = Utf8               Code\n",
    "  #12 = Utf8               LineNumberTable\n",
    "  #13 = Utf8               inc\n",
    "  #14 = Utf8               ()I\n",
    "  #15 = Utf8               SourceFile\n",
    "  #16 = Utf8               App.java\n",
    "  #17 = NameAndType        #9:#10         // \"<init>\":()V\n",
    "  #18 = NameAndType        #8:#7          // n:I\n",
    "  #19 = NameAndType        #6:#7          // m:I\n",
    "  #20 = Utf8               App\n",
    "  #21 = Utf8               java/lang/Object\n",
    "...\n",
    "```\n",
    "`javap`字节码分析中输出的信息也表明：第一项`Methodref`的索引为`#5.#17`，这和我们计算出的一样。\n",
    "\n",
    "* `Methodref`的第二个索引值索引到第`#5`项常量是一个`CONSTANT_Class_info`型，其又索引到`#21`项是一个字符串，其值为`java/lang/Object`。\n",
    "\n",
    "* `Methodref`的第二个索引值索引到第`#17`个常量，该常量是一个`NameAndType`型，用于标识方法的描述符，可以看到第`#17`项常量和`#9`和`#10`都有关，这两个常量都是字符串类型，其值分别为`<init>`和`()V`。\n",
    "\n",
    "其实`javap`分析器已经将`#1`号常量的值计算出来了：`java/lang/Object.\"<init>\":()V`"
   ]
  },
  {
   "cell_type": "markdown",
   "metadata": {},
   "source": [
    "在这里还要简述Java中表示类型的规则：\n",
    "\n",
    "* 通常对于基本类型，例如`int`，`double`等，使用大写的`I`或`D`来表示，对于`void`这种特殊类型就使用`V`表示。\n",
    "\n",
    "* 而对于Java中的对象类型，例如`String`类型，使用`Ljava.lang.String`表示，前面的`L`表示对象类型。\n",
    "\n",
    "* 如果是数组的话，例如一个整形数组则使用`[I`来表示，如果是字符串数组则使用`[Ljava.lang.String`，需要注意的是，这只是一维数组，如果是二维则使用`[[Ljava.lang.String`。\n",
    "\n",
    "Java字节码中描述对象方法的规则是：描述方法中参数的类型以及返回值类型。例如对于一个以下类型的方法\n",
    "\n",
    "```Java\n",
    "String getName(int index, double age, String[][] tag);\n",
    "```\n",
    "则可以表述成：\n",
    "\n",
    "```shell\n",
    "(ID[[Ljava.lang.String)Ljava.lang.String\n",
    "```\n",
    "刚才例子中的`()V`即代表该方法没有参数且返回值为`void`。"
   ]
  },
  {
   "cell_type": "markdown",
   "metadata": {},
   "source": [
    "### 访问标志\n",
    "\n",
    "在常量池结束之后紧接着是访问标志：`ACCESS_Flag`。这个标志标识着该类是否为`public`等信息，这个访问标志使用两个字节表示，在该例子中：\n",
    "\n",
    "```shell\n",
    "offset |  0   1   2   3   4   5   6   7   8   9   A   B   C   D   E   F\n",
    "-----------------------------------------------------------------------\n",
    "                              ... \n",
    "0x0090 |                                                        ...  00  \n",
    "0x00A0 | 21 ...\n",
    "```\n",
    "该访问标志为：`0x0021`。"
   ]
  },
  {
   "cell_type": "markdown",
   "metadata": {},
   "source": [
    "### 类索引，父类索引及接口索引集合\n",
    "\n",
    "这个字段紧接着访问标志，用于标识该类属于的类，以及其父类和实现的接口信息。类索引和父类索引均使用一个字节表示，接口索引也使用一个字节表示，在接口索引出现之前先表示集合的大小。本例中的这些索引为：\n",
    "\n",
    "```shell\n",
    "offset |  0   1   2   3   4   5   6   7   8   9   A   B   C   D   E   F\n",
    "-----------------------------------------------------------------------\n",
    "...\n",
    "0x00A0 |...  00  04  00  05  00  00  ...\n",
    "```\n",
    "可以看到，该字节码的本类索引值为`0x0004`，父类索引值为`0x0005`分别索引到常量池中的第4个常量和第5个常量。查表得这两个常量都是`CONSTANT_Class_info`类型，代表`App`和`java.lang.Object`。而该类没有实现任何接口，因此接口索引集合的大小表示为`0x0000`，也就是没有接口索引。"
   ]
  },
  {
   "cell_type": "markdown",
   "metadata": {},
   "source": [
    "### 字段表集合\n",
    "\n",
    "这个集合紧接着接口索引集合，用于表示类中的字段，注意方法中的临时变量并不在这里表示，字段表的结构如下所示：\n",
    "\n",
    "|类型|名称|数量|备注|\n",
    "|:-:|:-:|:-:|:-:|\n",
    "|u2|access_flags|1|访问标志位，用于标识该字段是否为`private`这样的信息|\n",
    "|u2|name_index|1|该字段的简单名称|\n",
    "|u2|descriptor_index|1|该字段的描述符，值类型|\n",
    "|u2|attributes_count|1|属性集个数|\n",
    "|attribute_info|attributes|attributes_count|具体的属性|\n",
    "\n",
    "本例中有两个字段分别是`m`和`n`，字节码中的表示为：\n",
    "\n",
    "```shell\n",
    "offset |  0   1   2   3   4   5   6   7   8   9   A   B   C   D   E   F\n",
    "-----------------------------------------------------------------------\n",
    "...  \n",
    "0x00A0 |                        ...  00  02  00  02  00  06  00  07  00  \n",
    "0x00B0 | 00  00  02  00  08  00  07  00  00 ...\n",
    "```\n",
    "可以看到字段集合的起始为字段集合的大小，这里是`0x0002`，代表有两个字段。然后紧接着就是第一个字段的`ACCESS_Flag`这里的意义和类的`ACCESS_Flag`相似，随后的两个字段分别是常量索引，代表该字段的简名以及描述符（`0x0006, 0x0007`）,最后一个是该字段属性列表的大小，属性用于表示该字段的一些特殊特征，这里为`0x0000`也就是属性列表为空。\n",
    "\n",
    "第二个字段的解释和上面完全一致。"
   ]
  },
  {
   "cell_type": "markdown",
   "metadata": {},
   "source": [
    "### 方法表集合\n",
    "\n",
    "方法表即一个类内部的各种方法的集合，它和字段表的结构非常相似，还是以文中的例子为例，其方法表集合如下面所示：\n",
    "\n",
    "```shell\n",
    "offset |  0   1   2   3   4   5   6   7   8   9   A   B   C   D   E   F\n",
    "----------------------------------------------------------------------- \n",
    "0x00B0 |                                ...  00  02  00  01  00  09  00  \n",
    "0x00C0 | 0A  00  01  00  0B  00  00  00  27  00  02  00  01  00  00  00  \n",
    "0x00D0 | 0B  2A  B7  00  01  2A  10  7B  B5  00  02  B1  00  00  00  01  \n",
    "0x00E0 | 00  0C  00  00  00  0A  00  02  00  00  00  01  00  04  00  04  \n",
    "0x00F0 | 00  01  00  0D  00  0E  00  01  00  0B  00  00  00  1F  00  02  \n",
    "0x0100 | 00  01  00  00  00  07  2A  B4  00  03  04  60  AC  00  00  00  \n",
    "0x0110 | 01  00  0C  00  00  00  06  00  01  00  00  00  06  00  01  ...\n",
    "```\n",
    "方发表的开头是方法表集合的大小，在这里是`0x0002`即为有两个方法表，接下来就进入方发表的正文部分，方法表的结构图下表所示：\n",
    "\n",
    "|类型|名称|数量|备注|\n",
    "|:-:|:-:|:-:|:-:|\n",
    "|u2|access_flags|1|访问标志位，用于标识该方法是否为`private`这样的信息|\n",
    "|u2|name_index|1|该方法的简单名称|\n",
    "|u2|descriptor_index|1|该方法的描述符，包括特征标和返回值类型|\n",
    "|u2|attributes_count|1|属性集个数|\n",
    "|attribute_info|attributes|attributes_count|具体的属性|"
   ]
  },
  {
   "cell_type": "markdown",
   "metadata": {},
   "source": [
    "在方法表中最重要的属性就是`Code`属性，它存放了该方法内容的全部编码。`Code`属性的表结构如下所示：\n",
    "\n",
    "|类型|名称|数量|备注|\n",
    "|:-:|:-:|:-:|:-:|\n",
    "|u2|attribute_name_index|1|`Code`属性在常量表中的索引号|\n",
    "|u4|attribute_length|1|属性的长度，注意：该长度不包含`attribute_name_index`和`attribute_length`两个字段|\n",
    "|u2|max_stack|1|栈帧中操作数栈的最大深度|\n",
    "|u2|max_locals|1|局部变量表的存储空间，单位为`slot`|\n",
    "|u4|code_length|1|字节码的长度|\n",
    "|u1|code|code_length|字节码的内容|\n",
    "|u2|exception_table_length|1|异常表的长度|\n",
    "|exception_info|exception_table|exception_tab;e_lenght|异常表的内容|\n",
    "|u2|attributes_count|1|属性表长度|\n",
    "|attribute_info|attributes|attributes_count|例如用于标识字节码与源代码行号对应关系的`LineNumberTable`属性|"
   ]
  },
  {
   "cell_type": "markdown",
   "metadata": {},
   "source": [
    "最后，需要说一下方法表中的`max_locals`字段，该字段表示局部变量表中的存储空间，其基本单位为`slot`，这是Java虚拟机中存储分配的最基本单位，如果是`int`,`char`这样的数据类型，那么就会给其分配一个`slot`，而如果是`double`或`long`型那么就会分配两个`slot`。有的方法即使没有内部变量但是其`max_locals`也不为0，例如：\n",
    "\n",
    "```shell\n",
    "public int inc();\n",
    "    descriptor: ()I\n",
    "    flags: (0x0001) ACC_PUBLIC\n",
    "    Code:\n",
    "      stack=2, locals=1, args_size=1\n",
    "         0: aload_0\n",
    "         1: getfield      #3                  // Field m:I\n",
    "         4: iconst_1\n",
    "         5: iadd\n",
    "         6: ireturn\n",
    "      LineNumberTable:\n",
    "        line 6: 0\n",
    "```"
   ]
  },
  {
   "cell_type": "markdown",
   "metadata": {},
   "source": [
    "`inc`方法没有局部变量，方法中引用的是类的字段，但是它的`max_locals`却不为0，这是因为类中的方法都有一个`this`对象，这个对象在方法中是隐式传入的，`max_locals`中的变量指的就是`this`对象。"
   ]
  },
  {
   "cell_type": "markdown",
   "metadata": {},
   "source": [
    "### 类属性\n",
    "\n",
    "方法表集合结束后就是类属性，在本例中类属性如下所示：\n",
    "\n",
    "```shell\n",
    "offset |  0   1   2   3   4   5   6   7   8   9   A   B   C   D   E   F\n",
    "----------------------------------------------------------------------- \n",
    "0x0110 |                                                        ...  00  \n",
    "0x0020 | 0F  00  00  00  02  00  10\n",
    "```\n",
    "查常量表可知`0x000F`是一个`SourceFile`类型的表，根据`SourceFile`表的结构可得该属性的值为：`App.java`"
   ]
  }
 ],
 "metadata": {
  "kernelspec": {
   "display_name": "Python 3",
   "language": "python",
   "name": "python3"
  },
  "language_info": {
   "codemirror_mode": {
    "name": "ipython",
    "version": 3
   },
   "file_extension": ".py",
   "mimetype": "text/x-python",
   "name": "python",
   "nbconvert_exporter": "python",
   "pygments_lexer": "ipython3",
   "version": "3.5.4"
  }
 },
 "nbformat": 4,
 "nbformat_minor": 2
}
